setup.py
geogotchi/__init__.py
geogotchi/base.py
geogotchi/constants.py
geogotchi/errors.py
geogotchi.egg-info/PKG-INFO
geogotchi.egg-info/SOURCES.txt
geogotchi.egg-info/dependency_links.txt
geogotchi.egg-info/requires.txt
geogotchi.egg-info/top_level.txt