Metadata-Version: 1.0
Name: geogotchi
Version: 0.1.1
Summary: Library for working with geonames.org services
Home-page: https://github.com/Memoto/geogotchi/
Author: Simon Pantzare
Author-email: simon+geogotchi@pewpewlabs.com
License: MIT
Platform: Posix; MacOS X; Windows
Classifier: Development Status :: 3 - Alpha
Classifier: Topic :: Internet
Classifier: Intended Audience :: Developers
Classifier: License :: OSI Approved :: MIT License
Classifier: Operating System :: OS Independent
Classifier: Programming Language :: Python :: 2
Classifier: Programming Language :: Python :: 2.7
